crewai_aisearchapi/__init__.py
crewai_aisearchapi/tool.py
crewai_aisearchapi/utils.py
crewai_aisearchapi-1.0.8.dist-info/licenses/LICENSE
crewai_aisearchapi-1.0.8.dist-info/METADATA
crewai_aisearchapi-1.0.8.dist-info/WHEEL
crewai_aisearchapi-1.0.8.dist-info/top_level.txt
crewai_aisearchapi-1.0.8.dist-info/RECORD
