Metadata-Version: 2.4
Name: crewai-aisearchapi
Version: 1.0.8
Summary: AI Search API integration for CrewAI - Enable intelligent web search in your crews
Author-email: AI Search API <admin@aisearchapi.io>
License: MIT License
Project-URL: Homepage, https://github.com/aisearchapi/crewai-aisearchapi
Project-URL: Documentation, https://docs.aisearchapi.io/integrations/crewai
Project-URL: Repository, https://github.com/aisearchapi/crewai-aisearchapi
Keywords: crewai,ai-agents,search-api,aisearchapi,web-search,intelligent-search,research-automation
Classifier: Development Status :: 4 - Beta
Classifier: Intended Audience :: Developers
Classifier: License :: OSI Approved :: MIT License
Classifier: Operating System :: OS Independent
Classifier: Programming Language :: Python :: 3
Classifier: Programming Language :: Python :: 3.8
Classifier: Programming Language :: Python :: 3.9
Classifier: Programming Language :: Python :: 3.10
Classifier: Programming Language :: Python :: 3.11
Classifier: Programming Language :: Python :: 3.12
Classifier: Topic :: Scientific/Engineering :: Artificial Intelligence
Requires-Python: >=3.8
License-File: LICENSE
Requires-Dist: crewai>=0.30.0
Requires-Dist: aisearchapi-client>=1.0.7
Requires-Dist: pydantic>=2.0.0
Provides-Extra: dev
Requires-Dist: pytest>=7.0; extra == "dev"
Requires-Dist: pytest-cov>=4.0; extra == "dev"
Requires-Dist: black>=23.0; extra == "dev"
Requires-Dist: ruff>=0.1.0; extra == "dev"
Requires-Dist: mypy>=1.0; extra == "dev"
Dynamic: license-file
